{
  "project_info": {
    "project_number": "1038491331080",
    "project_id": "fir-ejm-80836",
    "storage_bucket": "fir-ejm-80836.firebasestorage.app"
  },
  "client": [
    {
      "client_info": {
        "mobilesdk_app_id": "1:1038491331080:android:e2f0f01e04175171eaffbd",
        "android_client_info": {
          "package_name": "com.example.loginfirebase"
        }
      },
      "oauth_client": [],
      "api_key": [
        {
          "current_key": "AIzaSyBZdMimAfcOn1uZUk-LnqYajXjSfWFGj1A"
        }
      ],
      "services": {
        "appinvite_service": {
          "other_platform_oauth_client": []
        }
      }
    }
  ],
  "configuration_version": "1"
}